{"version":"5","id":"clnyj5s7t008qqi1p48dh55w1","name":"PLACA","groups":[{"id":"fso4hgzwuhb2gxffu8ne21k6","title":"Start","graphCoordinates":{"x":-446,"y":8},"blocks":[{"id":"l2shhnik910q0937sp8rqx0a","groupId":"fso4hgzwuhb2gxffu8ne21k6","outgoingEdgeId":"ty5xkydx5mrpa4ta47nmwn9g","type":"start","label":"Start"}]},{"id":"eqm5zly8rmbetfcz5ean84ul","title":"API","graphCoordinates":{"x":467,"y":491},"blocks":[{"id":"o70hp147yr7lqd8snarne1mh","groupId":"eqm5zly8rmbetfcz5ean84ul","type":"Wait","options":{"secondsToWaitFor":"1"}},{"id":"smf7y1bcj48b4tes1e3hdwnn","groupId":"eqm5zly8rmbetfcz5ean84ul","type":"text","content":{"richText":[{"type":"p","children":[{"text":"Consultando aguarde...","italic":true}]}]}},{"id":"amb46kfmtopuvuw8s7k0mlzg","groupId":"eqm5zly8rmbetfcz5ean84ul","type":"Wait","options":{"secondsToWaitFor":"1"}},{"id":"xutcgfbjx0fbc1pk712hb9x6","groupId":"eqm5zly8rmbetfcz5ean84ul","outgoingEdgeId":"iil6ycxshi81sdw7881dc517","type":"Webhook","options":{"variablesForTest":[],"responseVariableMapping":[{"id":"uur5y9juyu877z3v8pt8ke70","variableId":"vaonamg0tolpeq9bseemsr282","bodyPath":"data.data.modelo"},{"id":"weaj7h31mi4d50o3qaodej7k","variableId":"vqhlrf94yvd4qvdnoadkr2b55","bodyPath":"data.data.marca"},{"id":"z8kj1pdxiweqwgyit8de4v7y","variableId":"vxo1s1un5d4kb7a5k7vbw8dy2","bodyPath":"data.data.nacionalidade"},{"id":"q9nry3w6ju9tqvh3lpyjo8qf","variableId":"vfcycmk0a9u0bft8rurmhu9fo","bodyPath":"data.data.anoModelo"},{"id":"mwkkde7xx35shwtos36t6opw","variableId":"ve09rsl59gt2iufchpvdnzvvl","bodyPath":"data.data.anoFabricacao"},{"id":"bx4txiamc06uu76lic2utxr9","variableId":"vydg32q170co1s5cmjaai89hn","bodyPath":"data.data.chassi"},{"id":"ctaax2p57o6kamfelajbry64","variableId":"vwfmxujmi2sx75911qoiw7w0b","bodyPath":"data.data.renavam"},{"id":"y7aftwij3h5an6pjf44t24f2","variableId":"vmzfv53jrn7t3s8qjztopuzrh","bodyPath":"data.data.motor"},{"id":"qe4ix439yuak5axy4i1bc5vj","variableId":"vj9ud743wrdnkta2w5hxx6q5h","bodyPath":"data.data.cilindradas"},{"id":"ph8fbaq5mtyvzvk6dalm21hr","variableId":"vewiqiw4nvh8cx37krgo2uop9","bodyPath":"data.data.peso"},{"id":"pm78mup33qgenobx3bo9xdl0","variableId":"vsl9brbf4jnx7ke3j0ykhv0bq","bodyPath":"data.data.uf"},{"id":"xj1yyj5311womk3h4w78zmxr","variableId":"vcjewjwiwy54vqi6nabg1b0ew","bodyPath":"data.data.placa"}],"isAdvancedConfig":true,"isCustomBody":false,"webhook":{"id":"yrt75adgx1yhj8f63w92rur8","queryParams":[],"headers":[{"id":"u2yyvdwywcx08fvan6vq8qm5","key":"Content-Type","value":"application/json"},{"id":"x10rter92jxoj7druimq8sam","key":"User-Agent","value":"Mozilla/5.0 (Macintosh; Intel Mac OS X 10_11_5)"}],"method":"GET","url":"{{APIplaca}}{{placa}}","body":"{\n\"placa\": \"jhq1210\"\n}"}}}]},{"id":"r8i2026h5txbe52409f72hhs","title":"Consulta","graphCoordinates":{"x":465,"y":-55},"blocks":[{"id":"vzd7j5s6rlscyg6j61vs4dtz","groupId":"r8i2026h5txbe52409f72hhs","type":"Set variable","options":{"variableId":"vvqlr27wlz1jeyya34fjkujob","expressionToEvaluate":"https://api.brabocar.com.br/api/Vehicle/"}},{"id":"ext1otzvnh50l0buzg1vb0e8","groupId":"r8i2026h5txbe52409f72hhs","type":"Wait","options":{"secondsToWaitFor":"1"}},{"id":"l7pdrzeg9ghm0u4mx7fhrqty","groupId":"r8i2026h5txbe52409f72hhs","type":"text","content":{"richText":[{"type":"p","children":[{"text":"Por favor, informe a placa que deseja consultar."}]},{"type":"p","children":[{"text":""}]},{"type":"p","children":[{"text":"EX: ABC1234","italic":true}]}]}},{"id":"nif0w9cjurx3b4o3dnioph4p","groupId":"r8i2026h5txbe52409f72hhs","type":"Wait","options":{"secondsToWaitFor":"1"}},{"id":"y4kp87daudqyxrsrmd55sxts","groupId":"r8i2026h5txbe52409f72hhs","outgoingEdgeId":"nhzmrd93q5v8mi4mncy96qrj","type":"text input","options":{"labels":{"placeholder":"","button":""},"variableId":"vmgk8r1tcnr2q815mmv7exe39","isLong":false}}]},{"id":"kx1xdwdrfnadwpc0gge85e8t","title":"Resultado","graphCoordinates":{"x":468,"y":1163},"blocks":[{"id":"e2lndkckk4nlj5nmyjwhzcyw","groupId":"kx1xdwdrfnadwpc0gge85e8t","type":"Wait","options":{"secondsToWaitFor":"1"}},{"id":"hfc84wo3vllqk4p3xty930b4","groupId":"kx1xdwdrfnadwpc0gge85e8t","type":"Wait","options":{"secondsToWaitFor":"3"}},{"id":"ibitqx10nosw3x4lt2thceyl","groupId":"kx1xdwdrfnadwpc0gge85e8t","outgoingEdgeId":"emftazzsc4ct78bbxhncnr10","type":"text","content":{"richText":[{"type":"p","children":[{"text":"Seu carro é um "},{"bold":true,"text":"{{marca}}"},{"text":" modelo "},{"bold":true,"text":"{{modelo}} "},{"text":"ano "},{"bold":true,"text":"{{anoModelo}}"},{"text":"."}]},{"type":"p","children":[{"text":""}]},{"type":"p","children":[{"text":"Gostaria de saber algo mais?"}]}]}}]},{"id":"rvo5mjj2uzba8k76owx5ta1p","title":"jump","graphCoordinates":{"x":858,"y":1257},"blocks":[{"id":"k3nej08saz2x9xwcus1pn04z","groupId":"rvo5mjj2uzba8k76owx5ta1p","type":"Typebot link","options":{"typebotId":"clnudptgc000iqi1pipagr0cd","groupId":"jmfi67v8re2bjfhgietdgkm7","mergeResults":false}}]},{"id":"zr94vdxof5gm43tc1pjnvyvj","title":"Dados","graphCoordinates":{"x":862,"y":756},"blocks":[{"id":"t4o076hcnv211iqp9lxhum9b","groupId":"zr94vdxof5gm43tc1pjnvyvj","type":"text","content":{"richText":[{"type":"p","children":[{"bold":true,"text":"Placa: "},{"text":"{{data.data.placa}}"}]},{"type":"p","children":[{"bold":true,"text":"Modelo:"},{"text":" {{modelo}}"}]},{"type":"p","children":[{"bold":true,"text":"Marca: "},{"text":"{{marca}}"}]},{"type":"p","children":[{"bold":true,"text":"Nacionalidade: "},{"text":"{{nacionalidade}}"}]},{"type":"p","children":[{"bold":true,"text":"Ano mod:"},{"text":" {{anoModelo}}"}]},{"type":"p","children":[{"bold":true,"text":"Ano fab:"},{"text":" {{anoFabricacao}}"}]},{"type":"p","children":[{"bold":true,"text":"Chassi: "},{"text":"{{chassi}}"}]},{"type":"p","children":[{"bold":true,"text":"Renavam:"},{"text":" {{renavam}}"}]},{"type":"p","children":[{"bold":true,"text":"Motor:"},{"text":" {{motor}}"}]},{"type":"p","children":[{"bold":true,"text":"Cilindradas:"},{"text":" {{cilindradas}}"}]},{"type":"p","children":[{"bold":true,"text":"Peso:"},{"text":" {{peso}}"}]},{"type":"p","children":[{"bold":true,"text":"Uf:"},{"text":" {{uf}}"}]}]}}]}],"edges":[{"id":"nhzmrd93q5v8mi4mncy96qrj","from":{"groupId":"r8i2026h5txbe52409f72hhs","blockId":"y4kp87daudqyxrsrmd55sxts"},"to":{"groupId":"eqm5zly8rmbetfcz5ean84ul"}},{"id":"ty5xkydx5mrpa4ta47nmwn9g","from":{"groupId":"fso4hgzwuhb2gxffu8ne21k6","blockId":"l2shhnik910q0937sp8rqx0a"},"to":{"groupId":"r8i2026h5txbe52409f72hhs"}},{"id":"iil6ycxshi81sdw7881dc517","from":{"groupId":"eqm5zly8rmbetfcz5ean84ul","blockId":"xutcgfbjx0fbc1pk712hb9x6"},"to":{"groupId":"kx1xdwdrfnadwpc0gge85e8t"}},{"id":"emftazzsc4ct78bbxhncnr10","from":{"groupId":"kx1xdwdrfnadwpc0gge85e8t","blockId":"ibitqx10nosw3x4lt2thceyl"},"to":{"groupId":"rvo5mjj2uzba8k76owx5ta1p"}}],"variables":[{"id":"vmgk8r1tcnr2q815mmv7exe39","name":"placa"},{"id":"vaonamg0tolpeq9bseemsr282","name":"modelo"},{"id":"vqhlrf94yvd4qvdnoadkr2b55","name":"marca"},{"id":"vxo1s1un5d4kb7a5k7vbw8dy2","name":"nacionalidade"},{"id":"vfcycmk0a9u0bft8rurmhu9fo","name":"anoModelo"},{"id":"ve09rsl59gt2iufchpvdnzvvl","name":"anoFabricacao"},{"id":"vydg32q170co1s5cmjaai89hn","name":"chassi"},{"id":"vwfmxujmi2sx75911qoiw7w0b","name":"renavam"},{"id":"vmzfv53jrn7t3s8qjztopuzrh","name":"motor"},{"id":"vj9ud743wrdnkta2w5hxx6q5h","name":"cilindradas"},{"id":"vewiqiw4nvh8cx37krgo2uop9","name":"peso"},{"id":"vsl9brbf4jnx7ke3j0ykhv0bq","name":"uf"},{"id":"vcjewjwiwy54vqi6nabg1b0ew","name":"data.data.placa"},{"id":"vvqlr27wlz1jeyya34fjkujob","name":"APIplaca"}],"theme":{"general":{"font":"Open Sans","background":{"type":"Color","content":"#ffffff"}},"chat":{"hostAvatar":{"isEnabled":true},"hostBubbles":{"backgroundColor":"#F7F8FF","color":"#303235"},"guestBubbles":{"backgroundColor":"#FF8E21","color":"#FFFFFF"},"buttons":{"backgroundColor":"#0042DA","color":"#FFFFFF"},"inputs":{"backgroundColor":"#FFFFFF","color":"#303235","placeholderColor":"#9095A0"}}},"selectedThemeTemplateId":null,"settings":{"general":{"isBrandingEnabled":false,"isInputPrefillEnabled":true,"isHideQueryParamsEnabled":true,"rememberUser":{"isEnabled":false}},"typingEmulation":{"enabled":true,"speed":300,"maxDelay":1.5},"metadata":{"description":"Build beautiful conversational forms and embed them directly in your applications without a line of code. Triple your response rate and collect answers that has more value compared to a traditional form."}},"createdAt":"2023-10-20T11:31:12.281Z","updatedAt":"2023-11-23T16:21:33.346Z","icon":"https://cdn-icons-png.flaticon.com/512/290/290122.png","folderId":"clnueib0v001sqi1pmuy1525t","publicId":"placa-8dh55w1","customDomain":null,"workspaceId":"clnr64nj00001n21oaw5nat15","resultsTablePreferences":null,"isArchived":false,"isClosed":false,"whatsAppCredentialsId":null}